assign10/__init__.py
assign10/main.py
assin10-0.1.3.dist-info/METADATA
assin10-0.1.3.dist-info/WHEEL
assin10-0.1.3.dist-info/top_level.txt
assin10-0.1.3.dist-info/RECORD
